padding_oracle_attack/__init__.py
padding_oracle_attack/padding_oracle_attack.py
padding_oracle_attack-0.1.0.dist-info/LICENSE
padding_oracle_attack-0.1.0.dist-info/METADATA
padding_oracle_attack-0.1.0.dist-info/WHEEL
padding_oracle_attack-0.1.0.dist-info/top_level.txt
padding_oracle_attack-0.1.0.dist-info/RECORD
